{
"meta":{"test_sets":[],"test_metrics":[],"learn_metrics":[{"best_value":"Min","name":"RMSE"}],"launch_mode":"Train","parameters":"","iteration_count":200,"learn_sets":["learn"],"name":"experiment"},
"iterations":[
{"learn":[0.4909574301],"iteration":0,"passed_time":0.1457349466,"remaining_time":29.00125438},
{"learn":[0.4859258382],"iteration":1,"passed_time":0.1489131715,"remaining_time":14.74240398},
{"learn":[0.4819810773],"iteration":2,"passed_time":0.15199488,"remaining_time":9.980997119},
{"learn":[0.4781944295],"iteration":3,"passed_time":0.1550189836,"remaining_time":7.595930198},
{"learn":[0.4746620424],"iteration":4,"passed_time":0.1580793574,"remaining_time":6.165094938},
{"learn":[0.4714803684],"iteration":5,"passed_time":0.1610321652,"remaining_time":5.206706674},
{"learn":[0.4683481458],"iteration":6,"passed_time":0.1641226633,"remaining_time":4.525096288},
{"learn":[0.4652884074],"iteration":7,"passed_time":0.1676581536,"remaining_time":4.023795685},
{"learn":[0.4624515059],"iteration":8,"passed_time":0.1708761904,"remaining_time":3.626372485},
{"learn":[0.4599039687],"iteration":9,"passed_time":0.1737392885,"remaining_time":3.301046482},
{"learn":[0.4574864785],"iteration":10,"passed_time":0.1766644106,"remaining_time":3.035415781},
{"learn":[0.4550847214],"iteration":11,"passed_time":0.1796874535,"remaining_time":2.815103438},
{"learn":[0.4529446576],"iteration":12,"passed_time":0.1826897225,"remaining_time":2.627921392},
{"learn":[0.4510863783],"iteration":13,"passed_time":0.1858022806,"remaining_time":2.468516013},
{"learn":[0.4493281909],"iteration":14,"passed_time":0.1889952421,"remaining_time":2.33094132},
{"learn":[0.4476225548],"iteration":15,"passed_time":0.1918858216,"remaining_time":2.206686948},
{"learn":[0.4461033775],"iteration":16,"passed_time":0.1943418159,"remaining_time":2.092032489},
{"learn":[0.4446902007],"iteration":17,"passed_time":0.1965940301,"remaining_time":1.987784082},
{"learn":[0.4433180704],"iteration":18,"passed_time":0.1992204747,"remaining_time":1.897837153},
{"learn":[0.4419505521],"iteration":19,"passed_time":0.2016727243,"remaining_time":1.815054519},
{"learn":[0.440657507],"iteration":20,"passed_time":0.2040592129,"remaining_time":1.739361863},
{"learn":[0.4396805468],"iteration":21,"passed_time":0.2067716116,"remaining_time":1.672970312},
{"learn":[0.438539721],"iteration":22,"passed_time":0.209763189,"remaining_time":1.614264542},
{"learn":[0.4376976035],"iteration":23,"passed_time":0.2139610741,"remaining_time":1.569047877},
{"learn":[0.4368665443],"iteration":24,"passed_time":0.2186517977,"remaining_time":1.530562584},
{"learn":[0.4360095037],"iteration":25,"passed_time":0.222472211,"remaining_time":1.488852489},
{"learn":[0.4352773712],"iteration":26,"passed_time":0.2254524851,"remaining_time":1.444565923},
{"learn":[0.4346517682],"iteration":27,"passed_time":0.2294186764,"remaining_time":1.409286155},
{"learn":[0.4339660089],"iteration":28,"passed_time":0.2349425364,"remaining_time":1.385350818},
{"learn":[0.4332905724],"iteration":29,"passed_time":0.2382383519,"remaining_time":1.350017327},
{"learn":[0.4326899699],"iteration":30,"passed_time":0.2413816361,"remaining_time":1.315919242},
{"learn":[0.4321275695],"iteration":31,"passed_time":0.245199494,"remaining_time":1.287297343},
{"learn":[0.4317293319],"iteration":32,"passed_time":0.248300435,"remaining_time":1.256550686},
{"learn":[0.4311846015],"iteration":33,"passed_time":0.2515983803,"remaining_time":1.228392092},
{"learn":[0.4306906785],"iteration":34,"passed_time":0.2542994256,"remaining_time":1.198840149},
{"learn":[0.4302182992],"iteration":35,"passed_time":0.2565136964,"remaining_time":1.168562395},
{"learn":[0.4298876171],"iteration":36,"passed_time":0.2614840644,"remaining_time":1.151943311},
{"learn":[0.4295048029],"iteration":37,"passed_time":0.2654497533,"remaining_time":1.131654211},
{"learn":[0.4290169918],"iteration":38,"passed_time":0.2686523056,"remaining_time":1.109051826},
{"learn":[0.4286803162],"iteration":39,"passed_time":0.2746158649,"remaining_time":1.09846346},
{"learn":[0.4282903193],"iteration":40,"passed_time":0.2804997268,"remaining_time":1.087791623},
{"learn":[0.4280138129],"iteration":41,"passed_time":0.2841317785,"remaining_time":1.06887669},
{"learn":[0.4276703355],"iteration":42,"passed_time":0.2878405223,"remaining_time":1.050952605},
{"learn":[0.4272924402],"iteration":43,"passed_time":0.2909494842,"remaining_time":1.031548171},
{"learn":[0.4270097798],"iteration":44,"passed_time":0.2937559173,"remaining_time":1.011825937},
{"learn":[0.4266937193],"iteration":45,"passed_time":0.2975843098,"remaining_time":0.9962605154},
{"learn":[0.4264580741],"iteration":46,"passed_time":0.3013684346,"remaining_time":0.9810504361},
{"learn":[0.4261582419],"iteration":47,"passed_time":0.3045858889,"remaining_time":0.9645219815},
{"learn":[0.4259380859],"iteration":48,"passed_time":0.3075607817,"remaining_time":0.9477893478},
{"learn":[0.4256518632],"iteration":49,"passed_time":0.3106473858,"remaining_time":0.9319421574},
{"learn":[0.4253729943],"iteration":50,"passed_time":0.314842052,"remaining_time":0.9198326617},
{"learn":[0.4252034369],"iteration":51,"passed_time":0.318492898,"remaining_time":0.9064797866},
{"learn":[0.4249772266],"iteration":52,"passed_time":0.3229306682,"remaining_time":0.8956756268},
{"learn":[0.4248279167],"iteration":53,"passed_time":0.325770674,"remaining_time":0.8807873777},
{"learn":[0.4246705825],"iteration":54,"passed_time":0.3301604559,"remaining_time":0.8704230201},
{"learn":[0.4243681423],"iteration":55,"passed_time":0.3338219117,"remaining_time":0.8583992016},
{"learn":[0.424207139],"iteration":56,"passed_time":0.3373027556,"remaining_time":0.8462156852},
{"learn":[0.4240241282],"iteration":57,"passed_time":0.3520988093,"remaining_time":0.8620350159},
{"learn":[0.4238884522],"iteration":58,"passed_time":0.370339779,"remaining_time":0.8850493023},
{"learn":[0.4236580961],"iteration":59,"passed_time":0.3814305923,"remaining_time":0.8900047154},
{"learn":[0.4234250659],"iteration":60,"passed_time":0.3883834263,"remaining_time":0.8850048567},
{"learn":[0.4232902911],"iteration":61,"passed_time":0.3946991902,"remaining_time":0.8785240041},
{"learn":[0.4230881579],"iteration":62,"passed_time":0.3990607214,"remaining_time":0.8677987116},
{"learn":[0.4229422349],"iteration":63,"passed_time":0.4031373513,"remaining_time":0.8566668714},
{"learn":[0.4228148158],"iteration":64,"passed_time":0.4075346101,"remaining_time":0.8464180363},
{"learn":[0.4225186468],"iteration":65,"passed_time":0.4108458492,"remaining_time":0.8341415725},
{"learn":[0.4224135388],"iteration":66,"passed_time":0.4139987008,"remaining_time":0.8218183165},
{"learn":[0.4222951842],"iteration":67,"passed_time":0.4170506822,"remaining_time":0.8095689713},
{"learn":[0.4221742682],"iteration":68,"passed_time":0.420199396,"remaining_time":0.7977698678},
{"learn":[0.4219982033],"iteration":69,"passed_time":0.4235970633,"remaining_time":0.7866802604},
{"learn":[0.421883013],"iteration":70,"passed_time":0.427904312,"remaining_time":0.7774599471},
{"learn":[0.4217529306],"iteration":71,"passed_time":0.4302977942,"remaining_time":0.7649738564},
{"learn":[0.4216352746],"iteration":72,"passed_time":0.4329326921,"remaining_time":0.7531842726},
{"learn":[0.4214648166],"iteration":73,"passed_time":0.4361153184,"remaining_time":0.7425747314},
{"learn":[0.4213089349],"iteration":74,"passed_time":0.4389444632,"remaining_time":0.7315741054},
{"learn":[0.4211574834],"iteration":75,"passed_time":0.4421813754,"remaining_time":0.7214538229},
{"learn":[0.4209479836],"iteration":76,"passed_time":0.4445808047,"remaining_time":0.7101745322},
{"learn":[0.42081756],"iteration":77,"passed_time":0.4472047322,"remaining_time":0.6994740683},
{"learn":[0.4207060849],"iteration":78,"passed_time":0.4509376633,"remaining_time":0.6906766742},
{"learn":[0.4205608053],"iteration":79,"passed_time":0.4537779971,"remaining_time":0.6806669957},
{"learn":[0.4204731072],"iteration":80,"passed_time":0.4573926748,"remaining_time":0.6719719544},
{"learn":[0.420301238],"iteration":81,"passed_time":0.4599125374,"remaining_time":0.6618253587},
{"learn":[0.4201594525],"iteration":82,"passed_time":0.4634799196,"remaining_time":0.6533391638},
{"learn":[0.4199895098],"iteration":83,"passed_time":0.4670167736,"remaining_time":0.6449279254},
{"learn":[0.4199113376],"iteration":84,"passed_time":0.480946552,"remaining_time":0.6506923939},
{"learn":[0.4197706402],"iteration":85,"passed_time":0.4897657101,"remaining_time":0.6492243134},
{"learn":[0.4197159617],"iteration":86,"passed_time":0.4945109156,"remaining_time":0.6422957869},
{"learn":[0.4195084878],"iteration":87,"passed_time":0.498193505,"remaining_time":0.6340644609},
{"learn":[0.4192843854],"iteration":88,"passed_time":0.5091313623,"remaining_time":0.6349840585},
{"learn":[0.4191484512],"iteration":89,"passed_time":0.5219354184,"remaining_time":0.6379210669},
{"learn":[0.4190587112],"iteration":90,"passed_time":0.5257680647,"remaining_time":0.6297661434},
{"learn":[0.4189443517],"iteration":91,"passed_time":0.5312917452,"remaining_time":0.6236903096},
{"learn":[0.4188602454],"iteration":92,"passed_time":0.5385688577,"remaining_time":0.6196437395},
{"learn":[0.4187006476],"iteration":93,"passed_time":0.5471783536,"remaining_time":0.6170309093},
{"learn":[0.4185589208],"iteration":94,"passed_time":0.5513939832,"remaining_time":0.6094354551},
{"learn":[0.4184346729],"iteration":95,"passed_time":0.5551731156,"remaining_time":0.6014375419},
{"learn":[0.4182450227],"iteration":96,"passed_time":0.5590971424,"remaining_time":0.5936804708},
{"learn":[0.4181142876],"iteration":97,"passed_time":0.5626674906,"remaining_time":0.5856335107},
{"learn":[0.418000062],"iteration":98,"passed_time":0.5670859498,"remaining_time":0.5785422316},
{"learn":[0.4178912618],"iteration":99,"passed_time":0.5700096573,"remaining_time":0.5700096573},
{"learn":[0.4177997242],"iteration":100,"passed_time":0.5736083022,"remaining_time":0.562249722},
{"learn":[0.4176980157],"iteration":101,"passed_time":0.5763361119,"remaining_time":0.5537346958},
{"learn":[0.4176116821],"iteration":102,"passed_time":0.5790833035,"remaining_time":0.5453502955},
{"learn":[0.4175148993],"iteration":103,"passed_time":0.5829415208,"remaining_time":0.5380998654},
{"learn":[0.4174231292],"iteration":104,"passed_time":0.5852982848,"remaining_time":0.529555591},
{"learn":[0.4173170353],"iteration":105,"passed_time":0.5886270564,"remaining_time":0.5219900312},
{"learn":[0.4171986158],"iteration":106,"passed_time":0.5911247054,"remaining_time":0.513781286},
{"learn":[0.4171117684],"iteration":107,"passed_time":0.5937796086,"remaining_time":0.5058122592},
{"learn":[0.4169632987],"iteration":108,"passed_time":0.59734589,"remaining_time":0.4987016146},
{"learn":[0.4168493815],"iteration":109,"passed_time":0.600811015,"remaining_time":0.4915726486},
{"learn":[0.4167835676],"iteration":110,"passed_time":0.6039282667,"remaining_time":0.4842307724},
{"learn":[0.416701825],"iteration":111,"passed_time":0.6073178887,"remaining_time":0.4771783411},
{"learn":[0.4165598405],"iteration":112,"passed_time":0.6103723304,"remaining_time":0.4699326791},
{"learn":[0.4164532426],"iteration":113,"passed_time":0.6139649682,"remaining_time":0.4631665549},
{"learn":[0.4162480665],"iteration":114,"passed_time":0.6178609828,"remaining_time":0.4566798568},
{"learn":[0.4161007886],"iteration":115,"passed_time":0.6220286242,"remaining_time":0.450434521},
{"learn":[0.416003959],"iteration":116,"passed_time":0.6256596477,"remaining_time":0.4438440236},
{"learn":[0.4159134074],"iteration":117,"passed_time":0.6297597054,"remaining_time":0.4376296258},
{"learn":[0.4158057911],"iteration":118,"passed_time":0.6338638558,"remaining_time":0.4314535489},
{"learn":[0.4157027225],"iteration":119,"passed_time":0.6379296062,"remaining_time":0.4252864042},
{"learn":[0.4156064465],"iteration":120,"passed_time":0.6412342406,"remaining_time":0.4186570662},
{"learn":[0.4155251049],"iteration":121,"passed_time":0.6460895625,"remaining_time":0.4130736547},
{"learn":[0.4154388045],"iteration":122,"passed_time":0.6492574195,"remaining_time":0.4064457017},
{"learn":[0.4153931691],"iteration":123,"passed_time":0.6559488118,"remaining_time":0.4020331427},
{"learn":[0.4153317015],"iteration":124,"passed_time":0.6597819955,"remaining_time":0.3958691973},
{"learn":[0.4152057458],"iteration":125,"passed_time":0.6650829922,"remaining_time":0.390604297},
{"learn":[0.4150860624],"iteration":126,"passed_time":0.670756344,"remaining_time":0.3855528591},
{"learn":[0.4150123346],"iteration":127,"passed_time":0.6762928492,"remaining_time":0.3804147277},
{"learn":[0.4149349135],"iteration":128,"passed_time":0.6803732354,"remaining_time":0.3744689901},
{"learn":[0.4148431393],"iteration":129,"passed_time":0.6844118426,"remaining_time":0.3685294537},
{"learn":[0.4147547509],"iteration":130,"passed_time":0.6880013124,"remaining_time":0.3623823706},
{"learn":[0.4147035955],"iteration":131,"passed_time":0.6918298193,"remaining_time":0.3563971796},
{"learn":[0.4145521157],"iteration":132,"passed_time":0.6957353446,"remaining_time":0.3504832187},
{"learn":[0.4144656154],"iteration":133,"passed_time":0.7014329513,"remaining_time":0.3454819014},
{"learn":[0.4143697567],"iteration":134,"passed_time":0.7061906785,"remaining_time":0.3400177341},
{"learn":[0.4142928365],"iteration":135,"passed_time":0.7092271112,"remaining_time":0.3337539347},
{"learn":[0.4141425083],"iteration":136,"passed_time":0.7123523471,"remaining_time":0.3275780866},
{"learn":[0.4139860293],"iteration":137,"passed_time":0.7156128532,"remaining_time":0.3215072239},
{"learn":[0.4139121624],"iteration":138,"passed_time":0.7190924711,"remaining_time":0.315572955},
{"learn":[0.4138119042],"iteration":139,"passed_time":0.7222634912,"remaining_time":0.3095414962},
{"learn":[0.413704158],"iteration":140,"passed_time":0.7255917036,"remaining_time":0.3036163866},
{"learn":[0.413595773],"iteration":141,"passed_time":0.7288426422,"remaining_time":0.2976962905},
{"learn":[0.4135305585],"iteration":142,"passed_time":0.7320558085,"remaining_time":0.2917984691},
{"learn":[0.4134256474],"iteration":143,"passed_time":0.7357002359,"remaining_time":0.2861056473},
{"learn":[0.4132938279],"iteration":144,"passed_time":0.7405568981,"remaining_time":0.2809008924},
{"learn":[0.4132056811],"iteration":145,"passed_time":0.7444306199,"remaining_time":0.2753373526},
{"learn":[0.4131240346],"iteration":146,"passed_time":0.7481842915,"remaining_time":0.2697535201},
{"learn":[0.413022944],"iteration":147,"passed_time":0.7528159715,"remaining_time":0.2645029089},
{"learn":[0.4128708739],"iteration":148,"passed_time":0.7568206086,"remaining_time":0.2590459801},
{"learn":[0.4127818133],"iteration":149,"passed_time":0.7595452295,"remaining_time":0.2531817432},
{"learn":[0.4126769522],"iteration":150,"passed_time":0.7637345895,"remaining_time":0.2478344032},
{"learn":[0.4125570517],"iteration":151,"passed_time":0.7690034196,"remaining_time":0.2428431851},
{"learn":[0.4125091319],"iteration":152,"passed_time":0.7751797607,"remaining_time":0.238127116},
{"learn":[0.4123896114],"iteration":153,"passed_time":0.7827959426,"remaining_time":0.2338221647},
{"learn":[0.4122706363],"iteration":154,"passed_time":0.7864191704,"remaining_time":0.228315243},
{"learn":[0.4121663486],"iteration":155,"passed_time":0.7908637698,"remaining_time":0.2230641402},
{"learn":[0.4120471782],"iteration":156,"passed_time":0.7957823448,"remaining_time":0.2179531263},
{"learn":[0.4119426454],"iteration":157,"passed_time":0.8002980055,"remaining_time":0.2127374445},
{"learn":[0.4117626869],"iteration":158,"passed_time":0.8062807331,"remaining_time":0.2079088683},
{"learn":[0.41161158],"iteration":159,"passed_time":0.8130303093,"remaining_time":0.2032575773},
{"learn":[0.4114765538],"iteration":160,"passed_time":0.818303465,"remaining_time":0.1982225785},
{"learn":[0.4113787397],"iteration":161,"passed_time":0.8219480334,"remaining_time":0.1928026251},
{"learn":[0.4112307601],"iteration":162,"passed_time":0.8284786187,"remaining_time":0.1880595638},
{"learn":[0.4111031831],"iteration":163,"passed_time":0.8322859945,"remaining_time":0.1826969256},
{"learn":[0.4109698479],"iteration":164,"passed_time":0.8382017567,"remaining_time":0.1778003726},
{"learn":[0.4109183126],"iteration":165,"passed_time":0.8418348666,"remaining_time":0.1724240088},
{"learn":[0.4108771166],"iteration":166,"passed_time":0.8447752511,"remaining_time":0.1669316364},
{"learn":[0.4107460175],"iteration":167,"passed_time":0.8476575575,"remaining_time":0.1614585824},
{"learn":[0.4106737739],"iteration":168,"passed_time":0.8514118467,"remaining_time":0.1561761376},
{"learn":[0.4105744139],"iteration":169,"passed_time":0.8545901817,"remaining_time":0.1508100321},
{"learn":[0.410498182],"iteration":170,"passed_time":0.8578589925,"remaining_time":0.1454848584},
{"learn":[0.4104158405],"iteration":171,"passed_time":0.8615235629,"remaining_time":0.1402480219},
{"learn":[0.410248433],"iteration":172,"passed_time":0.8728532456,"remaining_time":0.136225651},
{"learn":[0.4101243503],"iteration":173,"passed_time":0.8763221736,"remaining_time":0.1309446926},
{"learn":[0.4100454038],"iteration":174,"passed_time":0.8804017437,"remaining_time":0.1257716777},
{"learn":[0.409878975],"iteration":175,"passed_time":0.884261716,"remaining_time":0.1205811431},
{"learn":[0.4097912896],"iteration":176,"passed_time":0.8882799899,"remaining_time":0.1154262134},
{"learn":[0.4096616589],"iteration":177,"passed_time":0.8919093927,"remaining_time":0.1102359924},
{"learn":[0.4095887759],"iteration":178,"passed_time":0.8951106248,"remaining_time":0.1050129783},
{"learn":[0.4095017646],"iteration":179,"passed_time":0.8985490103,"remaining_time":0.09983877892},
{"learn":[0.4094195167],"iteration":180,"passed_time":0.9020866496,"remaining_time":0.09469417868},
{"learn":[0.4092977843],"iteration":181,"passed_time":0.9050536424,"remaining_time":0.0895107998},
{"learn":[0.4091679337],"iteration":182,"passed_time":0.9084412098,"remaining_time":0.08439071348},
{"learn":[0.4090805907],"iteration":183,"passed_time":0.912265518,"remaining_time":0.07932743634},
{"learn":[0.4089947049],"iteration":184,"passed_time":0.9175813907,"remaining_time":0.07439849114},
{"learn":[0.4089049235],"iteration":185,"passed_time":0.922981011,"remaining_time":0.069471689},
{"learn":[0.4087702323],"iteration":186,"passed_time":0.927328277,"remaining_time":0.06446667166},
{"learn":[0.4086891719],"iteration":187,"passed_time":0.9331228941,"remaining_time":0.05956103579},
{"learn":[0.4086078436],"iteration":188,"passed_time":0.9379480006,"remaining_time":0.05458956617},
{"learn":[0.4084870009],"iteration":189,"passed_time":0.945852786,"remaining_time":0.04978172558},
{"learn":[0.4083723591],"iteration":190,"passed_time":0.9550289449,"remaining_time":0.0450013639},
{"learn":[0.4082235533],"iteration":191,"passed_time":0.9646289273,"remaining_time":0.04019287197},
{"learn":[0.4080813709],"iteration":192,"passed_time":0.9715096342,"remaining_time":0.03523610072},
{"learn":[0.4079628204],"iteration":193,"passed_time":0.9786104344,"remaining_time":0.0302663021},
{"learn":[0.4079055425],"iteration":194,"passed_time":0.9825349828,"remaining_time":0.02519320469},
{"learn":[0.4078194101],"iteration":195,"passed_time":0.9862029624,"remaining_time":0.02012659107},
{"learn":[0.4076741515],"iteration":196,"passed_time":0.9901300427,"remaining_time":0.01507812248},
{"learn":[0.4074918381],"iteration":197,"passed_time":0.994023431,"remaining_time":0.01004064072},
{"learn":[0.4074286113],"iteration":198,"passed_time":0.9977481116,"remaining_time":0.005013809606},
{"learn":[0.4073477327],"iteration":199,"passed_time":1.001095879,"remaining_time":0}
]}